cognitoauthenticator/__init__.py
cognitoauthenticator/cognitoauthenticator.py
cognitoauthenticator/common-credentials.txt
cognitoauthenticator/handlers.py
cognitoauthenticator/orm.py
cognitoauthenticator/crypto/__init__.py
cognitoauthenticator/crypto/crypto.py
cognitoauthenticator/crypto/encoding.py
cognitoauthenticator/crypto/signing.py
cognitoauthenticator/templates/authorization-area.html
cognitoauthenticator/templates/change-password-admin.html
cognitoauthenticator/templates/change-password.html
cognitoauthenticator/templates/my_message.html
cognitoauthenticator/templates/native-login.html
cognitoauthenticator/templates/page.html
cognitoauthenticator/templates/signup.html
cognitoauthenticator/tests/__init__.py
cognitoauthenticator/tests/test_authenticator.py
cognitoauthenticator/tests/test_orm.py
jupyterhub_cognitoauthenticator-1.0.0.dist-info/LICENSE
jupyterhub_cognitoauthenticator-1.0.0.dist-info/METADATA
jupyterhub_cognitoauthenticator-1.0.0.dist-info/WHEEL
jupyterhub_cognitoauthenticator-1.0.0.dist-info/top_level.txt
jupyterhub_cognitoauthenticator-1.0.0.dist-info/RECORD
