Metadata-Version: 2.1
Name: jupyterhub-cognitoauthenticator
Version: 1.0.0
Summary: JijZeptLab Native Authenticator
Home-page: https://github.com/Jij-Inc/cognitoauthenticator
Author: Leticia Portella
Author-email: leportella@protonmail.com
License: 3 Clause BSD
License-File: LICENSE
Requires-Dist: jupyterhub (>=1.3)
Requires-Dist: bcrypt
Requires-Dist: onetimepass
Requires-Dist: boto3
